mux/rtl/top.v
module mux16to1 (
	input wire [15:0] data_in,
	input wire [3:0] sel,
	input wire en,
	output reg y
);

always @(*) begin
	y = (!en) ? 1'b0 : data_in[sel];
end

endmodule

mux/tb/test_bench.v
`timescale 1ns/1ps
module test_bench;
	reg [15:0] data_in;
	reg [3:0] sel;
	reg en;
	wire y;
	
	mux16to1 uut(
		.data_in(data_in),
		.sel(sel),
		.en(en),
		.y(y)
	);

	integer i = 0;

	initial begin
		$dumpfile("test_bench.vcd");
		$dumpvars(0, test_bench);
		
		$display("-------------------------------------------------------------------------------");
		$display("------------------------TESTBENCH FOR MULTIPLEXER 16:1-------------------------");
		$display("-------------------------------------------------------------------------------");
		
		for (i = 0; i < 16; i = i + 1) begin
			en = 0;
			data_in = $random % 65535;
			sel = i;
			#1;
			check_result(1'b0);
			#10; 
		end

		for (i = 0; i < 16; i = i + 1) begin
			en = 1;
			data_in = $random % 65535;
			sel = i;
			#1;
			check_result(calc_expected(data_in,sel,en));
			#10;
		end

		for (i = 0; i < 20; i = i+ 1) begin
			en = $random % 2;
			data_in = $random % 65535;
			sel = $random % 16;
			#1;
			check_result(calc_expected(data_in,sel,en));
			#10;
		end

		#100;
		$finish;

	end

	function calc_expected (input [15:0] in, input [3:0] sel_val, input en_val);
		begin
			calc_expected = (!en_val) ? 0: in[sel_val];
		end
	endfunction


	task check_result;
		input expected_result;
		begin
			$display("At time: %t, en = 1'b%b, sel = 4'b%b, data_in = 16'b%b", $time, en, sel, data_in);
			if ( y == expected_result) begin
				$display("-------------------------------------------------------------------------------");
				$display("PASSED: expected: 1'b%b, Got: 1'b%b", expected_result, y);
				$display("-------------------------------------------------------------------------------");
			end else begin
				$display("-------------------------------------------------------------------------------");
				$display("FAILED: expected: 1'b%b, Got: 1'b%b", expected_result, y);
				$display("-------------------------------------------------------------------------------");
			end
		end
	endtask
endmodule

mux/sim/test_bench.vcd
$date
	Wed Dec 18 15:04:43 2024
$end
$version
	Icarus Verilog
$end
$timescale
	1ps
$end
$scope module test_bench $end
$var wire 1 ! y $end
$var reg 16 " data_in [15:0] $end
$var reg 1 # en $end
$var reg 4 $ sel [3:0] $end
$var integer 32 % i [31:0] $end
$scope function calc_expected $end
$var reg 1 & en_val $end
$var reg 16 ' in [15:0] $end
$var reg 4 ( sel_val [3:0] $end
$upscope $end
$scope module uut $end
$var wire 16 ) data_in [15:0] $end
$var wire 1 # en $end
$var wire 4 * sel [3:0] $end
$var reg 1 ! y $end
$upscope $end
$scope task check_result $end
$var reg 1 + expected_result $end
$upscope $end
$upscope $end
$enddefinitions $end
$comment Show the parameter values. $end
$dumpall
$end
#0
$dumpvars
x+
b0 *
b100011100111001 )
bx (
bx '
x&
b0 %
b0 $
0#
b100011100111001 "
0!
$end
#1000
0+
#11000
b1 $
b1 *
b1111100001011 "
b1111100001011 )
b1 %
#22000
b10 $
b10 *
b101101010001110 "
b101101010001110 )
b10 %
#33000
b11 $
b11 *
b100001010100 "
b100001010100 )
b11 %
#44000
b100 $
b100 *
b1000000111000110 "
b1000000111000110 )
b100 %
#55000
b101 $
b101 *
b1110000001101100 "
b1110000001101100 )
b101 %
#66000
b110 $
b110 *
b11011100101000 "
b11011100101000 )
b110 %
#77000
b111 $
b111 *
b1101101101001001 "
b1101101101001001 )
b111 %
#88000
b1000 $
b1000 *
b1110001111110100 "
b1110001111110100 )
b1000 %
#99000
b1001 $
b1001 *
b1101001111100100 "
b1101001111100100 )
b1001 %
#110000
b1010 $
b1010 *
b10110010011010 "
b10110010011010 )
b1010 %
#121000
b1011 $
b1011 *
b1110101111001010 "
b1110101111001010 )
b1011 %
#132000
b1100 $
b1100 *
b1100111011000001 "
b1100111011000001 )
b1100 %
#143000
b1101 $
b1101 *
b11110110111010 "
b11110110111010 )
b1101 %
#154000
b1110 $
b1110 *
b110011011110111 "
b110011011110111 )
b1110 %
#165000
b1111 $
b1111 *
b11111111110 "
b11111111110 )
b1111 %
#176000
1!
b0 $
b0 *
b110011110111101 "
b110011110111101 )
1#
b0 %
#177000
1+
b110011110111101 '
b0 (
1&
#187000
b1 $
b1 *
b1010011110111110 "
b1010011110111110 )
b1 %
#188000
b1010011110111110 '
b1 (
#198000
b10 $
b10 *
b110101010010101 "
b110101010010101 )
b10 %
#199000
b110101010010101 '
b10 (
#209000
b11 $
b11 *
b10111001001010 "
b10111001001010 )
b11 %
#210000
b10111001001010 '
b11 (
#220000
0!
b100 $
b100 *
b101111101000101 "
b101111101000101 )
b100 %
#221000
0+
b101111101000101 '
b100 (
#231000
1!
b101 $
b101 *
b10001101111100 "
b10001101111100 )
b101 %
#232000
1+
b10001101111100 '
b101 (
#242000
0!
b110 $
b110 *
b1110001100100010 "
b1110001100100010 )
b110 %
#243000
0+
b1110001100100010 '
b110 (
#253000
b111 $
b111 *
b111111001000101 "
b111111001000101 )
b111 %
#254000
b111111001000101 '
b111 (
#264000
b1000 $
b1000 *
b110111011101001 "
b110111011101001 )
b1000 %
#265000
b110111011101001 '
b1000 (
#275000
b1001 $
b1001 *
b11000110010000 "
b11000110010000 )
b1001 %
#276000
b11000110010000 '
b1001 (
#286000
1!
b1010 $
b1010 *
b111011110110100 "
b111011110110100 )
b1010 %
#287000
1+
b111011110110100 '
b1010 (
#297000
0!
b1011 $
b1011 *
b11101001100 "
b11101001100 )
b1011 %
#298000
0+
b11101001100 '
b1011 (
#308000
b1100 $
b1100 *
b1110111011011000 "
b1110111011011000 )
b1100 %
#309000
b1110111011011000 '
b1100 (
#319000
b1101 $
b1101 *
b1101100100001100 "
b1101100100001100 )
b1101 %
#320000
b1101100100001100 '
b1101 (
#330000
b1110 $
b1110 *
b1010001010011 "
b1010001010011 )
b1110 %
#331000
b1010001010011 '
b1110 (
#341000
1!
b1111 $
b1111 *
b1000110001111101 "
b1000110001111101 )
b1111 %
#342000
1+
b1000110001111101 '
b1111 (
#352000
0!
b1010 $
b1010 *
b11000110000100 "
b11000110000100 )
0#
b0 %
#353000
0+
b11000110000100 '
b1010 (
0&
#363000
b11 $
b11 *
b100110110111 "
b100110110111 )
1#
b1 %
#364000
b100110110111 '
b11 (
1&
#374000
1!
b1011 $
b1011 *
b111111111111011 "
b111111111111011 )
b10 %
#375000
1+
b111111111111011 '
b1011 (
#385000
b1110 $
b1110 *
b1100101100011001 "
b1100101100011001 )
b11 %
#386000
b1100101100011001 '
b1110 (
#396000
0!
b11 $
b11 *
b101101010010101 "
b101101010010101 )
b100 %
#397000
0+
b101101010010101 '
b11 (
#407000
b1100 $
b1100 *
b1111000000111101 "
b1111000000111101 )
0#
b101 %
#408000
b1111000000111101 '
b1100 (
0&
#418000
b1 $
b1 *
b1010011010111000 "
b1010011010111000 )
b110 %
#419000
b1010011010111000 '
b1 (
#429000
b1001 $
b1001 *
b10111110011001 "
b10111110011001 )
b111 %
#430000
b10111110011001 '
b1001 (
#440000
b110 $
b110 *
b1100000010111000 "
b1100000010111000 )
1#
b1000 %
#441000
b1100000010111000 '
b110 (
1&
#451000
b1010 $
b1010 *
b1110000100110001 "
b1110000100110001 )
0#
b1001 %
#452000
b1110000100110001 '
b1010 (
0&
#462000
b101 $
b101 *
b111011100001001 "
b111011100001001 )
1#
b1010 %
#463000
b111011100001001 '
b101 (
1&
#473000
1!
b1010 $
b1010 *
b1111111000000111 "
b1111111000000111 )
b1011 %
#474000
1+
b1111111000000111 '
b1010 (
#484000
0!
b1 $
b1 *
b101010110111111 "
b101010110111111 )
0#
b1100 %
#485000
0+
b101010110111111 '
b1 (
0&
#495000
1!
b1100 $
b1100 *
b11100010000101 "
b11100010000101 )
1#
b1101 %
#496000
1+
b11100010000101 '
b1100 (
1&
#506000
b1000 $
b1000 *
b1110100101001000 "
b1110100101001000 )
b1110 %
#507000
b1110100101001000 '
b1000 (
#517000
0!
b1100 $
b1100 *
b10011001100100 "
b10011001100100 )
b1111 %
#518000
0+
b10011001100100 '
b1100 (
#528000
b1001 $
b1001 *
b111110001100111 "
b111110001100111 )
b10000 %
#529000
b111110001100111 '
b1001 (
#539000
b1 $
b1 *
b1010110011010110 "
b1010110011010110 )
0#
b10001 %
#540000
b1010110011010110 '
b1 (
0&
#550000
b10 $
b10 *
b1000010100101001 "
b1000010100101001 )
b10010 %
#551000
b1000010100101001 '
b10 (
#561000
b1101 $
b1101 *
b1010111111010 "
b1010111111010 )
b10011 %
#562000
b1010111111010 '
b1101 (
#572000
b10100 %
